arg_lmm/__main__.py
arg_lmm/arg_lmm.py
arg_lmm/arg_rhe.py
arg_lmm/third_party/chiscore/LICENSE.md
arg_lmm/third_party/chiscore/liu.py
arg_lmm-0.1.0.dist-info/METADATA
arg_lmm-0.1.0.dist-info/WHEEL
arg_lmm-0.1.0.dist-info/entry_points.txt
arg_lmm-0.1.0.dist-info/licenses/LICENSE
arg_lmm-0.1.0.dist-info/RECORD
