Metadata-Version: 2.4
Name: arg-lmm
Version: 0.1.0
Summary: Efficient complex trait analyses from ARG
Author: arg-lmm developers
License-File: LICENSE
Classifier: Development Status :: 4 - Beta
Classifier: License :: OSI Approved :: GNU General Public License v3 or later (GPLv3+)
Classifier: Programming Language :: Python :: 3 :: Only
Classifier: Programming Language :: Python :: 3.9
Classifier: Programming Language :: Python :: 3.10
Classifier: Programming Language :: Python :: 3.11
Classifier: Programming Language :: Python :: 3.12
Classifier: Programming Language :: Python :: 3.13
Requires-Python: >=3.9
Requires-Dist: arg-needle-lib>=1.2.1
Provides-Extra: dev
Requires-Dist: pytest; extra == 'dev'
